Metadata-Version: 2.1
Name: just-test-framework
Version: 99.99.999
Summary: This is a just_test_framework
Home-page: https://3bf2562a.log.dnslog.sbs.
Author: viyidem798@sfxeur.com
Author-email: viyidem798@sfxeur.com
License: UNKNOWN
Platform: UNKNOWN
Classifier: Programming Language :: Python :: 3
Classifier: License :: OSI Approved :: MIT License
Classifier: Operating System :: OS Independent
Requires-Python: >=2.5
